ostracker/__init__.py
ostracker/test_lib.py
ostracker-0.0.8.dist-info/LICENSE
ostracker-0.0.8.dist-info/METADATA
ostracker-0.0.8.dist-info/WHEEL
ostracker-0.0.8.dist-info/top_level.txt
ostracker-0.0.8.dist-info/RECORD
