Metadata-Version: 2.2
Name: ostracker
Version: 0.0.8
Summary: Python client library for ostracker.xyz
Home-page: https://ostracker.xyz
Author: ostracker.xyz
Author-email: admin@ostracker.xyz
Requires-Python: >=3.6
License-File: LICENSE
Dynamic: author
Dynamic: author-email
Dynamic: description-content-type
Dynamic: home-page
Dynamic: requires-python
Dynamic: summary
